LICENSE.txt
README.md
setup.py
cg_api/__init__.py
cg_api.egg-info/PKG-INFO
cg_api.egg-info/SOURCES.txt
cg_api.egg-info/dependency_links.txt
cg_api.egg-info/requires.txt
cg_api.egg-info/top_level.txt
cg_api/api/__init__.py
cg_api/api/coingecko_api.py
cg_api/config/__init__.py
cg_api/config/api_config.py
cg_api/util/__init__.py
cg_api/util/api_util.py